Metadata-Version: 1.0
Name: gb-distrib
Version: 1.0
Summary: Gaussian and Binomial Distributions
Home-page: UNKNOWN
Author: Andrei Ungureanu via Udacity
Author-email: UNKNOWN
License: UNKNOWN
Platform: UNKNOWN
